observerai/__init__.py
observerai/context/__init__.py
observerai/context/trace_context.py
observerai/driver/log_driver.py
observerai/metric/openai/completion/chat_create.py
observerai/openai/__init__.py
observerai/schema/eval_metric.py
observerai/schema/metric.py
observerai/schema/model_metric.py
observerai/schema/vector_store_metric.py
observerai-0.0.3.dist-info/METADATA
observerai-0.0.3.dist-info/WHEEL
observerai-0.0.3.dist-info/RECORD
