Metadata-Version: 2.3
Name: observerai
Version: 0.0.3
Summary: observerai - Structured Observability for Generative AI
Author: Nelson Frugeri Jr
Author-email: nelson.frugeri@icloud.com
Requires-Python: >=3.10,<4.0
Classifier: Programming Language :: Python :: 3
Classifier: Programming Language :: Python :: 3.10
Classifier: Programming Language :: Python :: 3.11
Classifier: Programming Language :: Python :: 3.12
Classifier: Programming Language :: Python :: 3.13
Provides-Extra: openai
Requires-Dist: openai (>=1.0.0,<2.0.0) ; extra == "openai"
Requires-Dist: pydantic (>=2.0,<3.0)
Requires-Dist: structlog (>=23.1.0,<24.0.0)
